Metadata-Version: 2.1
Name: taostd
Version: 0.5.4
Summary: taostd is a simple sql executor for TDengine.
Home-page: https://github.com/nzhzds/taostd/taostd
Author: summry
Author-email: xiazhongbiao@126.com
License: UNKNOWN
Keywords: sql,taos,TDengine,Time Series Database,python
Platform: UNKNOWN
Requires-Python: >=3.6.0
